odoo/addons/pim/README.rst
odoo/addons/pim/__init__.py
odoo/addons/pim/__manifest__.py
odoo/addons/pim/data/ir_module_category_data.xml
odoo/addons/pim/i18n/it.po
odoo/addons/pim/i18n/pim.pot
odoo/addons/pim/readme/CONFIGURE.md
odoo/addons/pim/readme/CONTRIBUTORS.md
odoo/addons/pim/readme/DESCRIPTION.md
odoo/addons/pim/readme/ROADMAP.md
odoo/addons/pim/readme/USAGE.md
odoo/addons/pim/security/pim_security.xml
odoo/addons/pim/static/description/icon.png
odoo/addons/pim/static/description/index.html
odoo/addons/pim/views/attribute_attribute.xml
odoo/addons/pim/views/attribute_group.xml
odoo/addons/pim/views/attribute_set.xml
odoo/addons/pim/views/pim_view.xml
odoo/addons/pim/views/product_attribute_value.xml
odoo/addons/pim/views/product_view.xml
odoo_addon_pim-18.0.1.0.0.4.dist-info/METADATA
odoo_addon_pim-18.0.1.0.0.4.dist-info/WHEEL
odoo_addon_pim-18.0.1.0.0.4.dist-info/top_level.txt
odoo_addon_pim-18.0.1.0.0.4.dist-info/RECORD
